csv2sendy/__init__.py
csv2sendy/cli.py
csv2sendy/py.typed
csv2sendy/core/__init__.py
csv2sendy/core/processor.py
csv2sendy/core/py.typed
csv2sendy/web/__init__.py
csv2sendy/web/app.py
csv2sendy/web/py.typed
tests/__init__.py
tests/test_processor.py
tests/test_web.py
csv2sendy-1.0.4.dist-info/LICENSE
csv2sendy-1.0.4.dist-info/METADATA
csv2sendy-1.0.4.dist-info/WHEEL
csv2sendy-1.0.4.dist-info/entry_points.txt
csv2sendy-1.0.4.dist-info/top_level.txt
csv2sendy-1.0.4.dist-info/RECORD
