Metadata-Version: 2.1
Name: csv2sendy
Version: 1.0.4
Summary: A CSV processor for Sendy.co with Brazilian data format support
Home-page: https://github.com/skaisser/csv2sendy
Author: Shirleyson Kaisser
Author-email: skaisser@gmail.com
Project-URL: Bug Tracker, https://github.com/skaisser/csv2sendy/issues
Project-URL: Documentation, https://csv2sendy.readthedocs.io/
Keywords: csv,sendy,email,contacts,brazil
Classifier: Development Status :: 5 - Production/Stable
Classifier: Intended Audience :: Developers
Classifier: License :: OSI Approved :: MIT License
Classifier: Operating System :: OS Independent
Classifier: Programming Language :: Python :: 3
Classifier: Programming Language :: Python :: 3.9
Classifier: Programming Language :: Python :: 3.10
Classifier: Programming Language :: Python :: 3.11
Classifier: Topic :: Software Development :: Libraries :: Python Modules
Classifier: Topic :: Text Processing :: General
Requires-Python: >=3.9
License-File: LICENSE
Requires-Dist: pandas>=1.3.0
Requires-Dist: email-validator>=1.1.0
Requires-Dist: flask>=2.0.0
Requires-Dist: werkzeug>=2.0.0
Provides-Extra: dev
Requires-Dist: pytest>=7.0.0; extra == "dev"
Requires-Dist: pytest-cov>=4.0.0; extra == "dev"
Requires-Dist: mypy>=1.13.0; extra == "dev"
Requires-Dist: types-flask>=1.1.0; extra == "dev"
Requires-Dist: types-werkzeug>=1.0.0; extra == "dev"
Requires-Dist: pandas-stubs>=2.0.0; extra == "dev"
Provides-Extra: docs
Requires-Dist: sphinx>=7.0.0; extra == "docs"
Requires-Dist: sphinx-rtd-theme>=3.0.0; extra == "docs"
Requires-Dist: myst-parser>=3.0.0; extra == "docs"
Requires-Dist: furo>=2024.0.0; extra == "docs"
